mrverify/__init__.py
mrverify/__version__.py
mrverify/config/__init__.py
mrverify/config/ssbc.yaml
mrverify/notifications/__init__.py
mrverify/notifications/gmail/__init__.py
mrverify/notifications/gmail/template.html
mrverify/notifications/smtp/__init__.py
mrverify/notifications/smtp/template.html
mrverify/report/__init__.py
mrverify/report/template.html
mrverify/scanner/__init__.py
mrverify/scanner/siemens/__init__.py
mrverify/scanner/siemens/prisma.py
mrverify/scanner/siemens/skyra.py
mrverify-0.2.0.data/scripts/mrcheck.py
mrverify-0.2.0.dist-info/LICENSE
mrverify-0.2.0.dist-info/METADATA
mrverify-0.2.0.dist-info/WHEEL
mrverify-0.2.0.dist-info/top_level.txt
mrverify-0.2.0.dist-info/RECORD
